wish_cli/__init__.py
wish_cli/main.py
wish_cli/py.typed
wish_cli/cli/__init__.py
wish_cli/cli/hybrid.py
wish_cli/cli/hybrid_cli.py
wish_cli/cli/hybrid_ui.py
wish_cli/cli/handlers/__init__.py
wish_cli/cli/handlers/builtin.py
wish_cli/cli/handlers/scope.py
wish_cli/cli/handlers/status.py
wish_cli/commands/__init__.py
wish_cli/commands/slash_commands.py
wish_cli/commands/sliver.py
wish_cli/core/__init__.py
wish_cli/core/command_dispatcher.py
wish_cli/core/exploit_engine.py
wish_cli/core/job_manager.py
wish_cli/core/vulnerability_detector.py
wish_cli/core/handlers/__init__.py
wish_cli/core/handlers/builtin_commands.py
wish_cli/headless/__init__.py
wish_cli/headless/client.py
wish_cli/headless/events.py
wish_cli/headless/models.py
wish_cli/services/__init__.py
wish_cli/services/scope_manager.py
wish_cli/ui/__init__.py
wish_cli/ui/chat_ui_manager.py
wish_cli/ui/colors.py
wish_cli/ui/input_handler.py
wish_cli/ui/minimal_input_app.py
wish_cli/ui/performance_monitor.py
wish_cli/ui/prompt_modal.py
wish_cli/ui/streaming_handler.py
wish_cli/ui/ui_manager.py
wish_cli-0.7.0.dist-info/METADATA
wish_cli-0.7.0.dist-info/WHEEL
wish_cli-0.7.0.dist-info/entry_points.txt
wish_cli-0.7.0.dist-info/RECORD
