Metadata-Version: 2.4
Name: wish-cli
Version: 0.7.0
Summary: Main CLI application for wish
Project-URL: Homepage, https://github.com/SecDev-Lab/wish
Project-URL: Documentation, https://github.com/SecDev-Lab/wish/tree/main/docs
Project-URL: Repository, https://github.com/SecDev-Lab/wish
Project-URL: Issues, https://github.com/SecDev-Lab/wish/issues
Author-email: "SecDevLab Inc." <dev@secdevlab.com>
License-Expression: AGPL-3.0
Classifier: Development Status :: 3 - Alpha
Classifier: Environment :: Console
Classifier: Intended Audience :: Information Technology
Classifier: License :: OSI Approved :: MIT License
Classifier: Operating System :: POSIX :: Linux
Classifier: Programming Language :: Python :: 3
Classifier: Programming Language :: Python :: 3.11
Classifier: Programming Language :: Python :: 3.12
Classifier: Topic :: Security
Classifier: Topic :: System :: Networking
Requires-Python: >=3.11
Requires-Dist: click>=8.0.0
Requires-Dist: prompt-toolkit>=3.0.0
Requires-Dist: pydantic>=2.5.0
Requires-Dist: rich>=13.0.0
Requires-Dist: wish-ai==0.7.0
Requires-Dist: wish-c2==0.7.0
Requires-Dist: wish-core==0.7.0
Requires-Dist: wish-knowledge==0.7.0
Requires-Dist: wish-models==0.7.0
Requires-Dist: wish-tools==0.7.0
Provides-Extra: dev
Requires-Dist: mypy>=1.7.0; extra == 'dev'
Requires-Dist: pytest-asyncio>=0.21.0; extra == 'dev'
Requires-Dist: pytest-mock>=3.12.0; extra == 'dev'
Requires-Dist: pytest>=7.0.0; extra == 'dev'
Requires-Dist: ruff>=0.1.0; extra == 'dev'
